reservoir_sampling_cli-0.1.data/scripts/resamp
reservoir_sampling_cli-0.1.dist-info/DESCRIPTION.rst
reservoir_sampling_cli-0.1.dist-info/entry_points.txt
reservoir_sampling_cli-0.1.dist-info/METADATA
reservoir_sampling_cli-0.1.dist-info/pydist.json
reservoir_sampling_cli-0.1.dist-info/RECORD
reservoir_sampling_cli-0.1.dist-info/top_level.txt
reservoir_sampling_cli-0.1.dist-info/WHEEL
sampler/__init__.py
sampler/command_line.py
