Metadata-Version: 2.0
Name: reservoir-sampling-cli
Version: 0.1
Summary: A command line tool to randomly sample k items from an input S containing n items.
Home-page: https://github.com/RyanBalfanz/reservoir-sampling-cli
Author: Ryan Balfanz
Author-email: ryan@ryanbalfanz.net
License: MIT
Platform: UNKNOWN
